goliath_client/__init__.py
goliath_client/client.py
goliath_client/models.py
goliath_client-0.1.0.dist-info/LICENSE
goliath_client-0.1.0.dist-info/METADATA
goliath_client-0.1.0.dist-info/WHEEL
goliath_client-0.1.0.dist-info/top_level.txt
goliath_client-0.1.0.dist-info/RECORD
