Metadata-Version: 2.1
Name: goliath-client
Version: 0.1.0
Summary: A Python client library for the Goliath LLM API
Author: Goliath Team
License-File: LICENSE
Requires-Dist: requests>=2.25.0
Requires-Dist: pydantic>=2.0.0
